odoo/addons/web_tree_duplicate/README.rst
odoo/addons/web_tree_duplicate/__init__.py
odoo/addons/web_tree_duplicate/__manifest__.py
odoo/addons/web_tree_duplicate/i18n/ca.po
odoo/addons/web_tree_duplicate/i18n/es.po
odoo/addons/web_tree_duplicate/i18n/fr.po
odoo/addons/web_tree_duplicate/i18n/he_IL.po
odoo/addons/web_tree_duplicate/i18n/it.po
odoo/addons/web_tree_duplicate/i18n/pt.po
odoo/addons/web_tree_duplicate/i18n/pt_BR.po
odoo/addons/web_tree_duplicate/i18n/web_tree_duplicate.pot
odoo/addons/web_tree_duplicate/i18n/zh_CN.po
odoo/addons/web_tree_duplicate/readme/CONFIGURE.md
odoo/addons/web_tree_duplicate/readme/CONTRIBUTORS.md
odoo/addons/web_tree_duplicate/readme/DESCRIPTION.md
odoo/addons/web_tree_duplicate/readme/USAGE.md
odoo/addons/web_tree_duplicate/static/description/icon.png
odoo/addons/web_tree_duplicate/static/description/index.html
odoo/addons/web_tree_duplicate/static/description/screenshot-duplicate.png
odoo/addons/web_tree_duplicate/static/src/web_tree_duplicate.esm.js
odoo_addon_web_tree_duplicate-17.0.1.0.0.2.dist-info/METADATA
odoo_addon_web_tree_duplicate-17.0.1.0.0.2.dist-info/WHEEL
odoo_addon_web_tree_duplicate-17.0.1.0.0.2.dist-info/top_level.txt
odoo_addon_web_tree_duplicate-17.0.1.0.0.2.dist-info/RECORD
