Metadata-Version: 2.1
Name: odoo-addon-web_tree_duplicate
Version: 17.0.1.0.0.2
Requires-Python: >=3.10
Requires-Dist: odoo>=17.0a,<17.1dev
Summary: Duplicate records directly from the tree view.
Home-page: https://github.com/OCA/web
License: AGPL-3
Author: Hunki Enterprises BV, Onestein, Odoo Community Association (OCA)
Author-email: support@odoo-community.org
Classifier: Programming Language :: Python
Classifier: Framework :: Odoo
Classifier: Framework :: Odoo :: 17.0
Classifier: License :: OSI Approved :: GNU Affero General Public License v3
Classifier: Development Status :: 4 - Beta
